communex/__init__.py
communex/_common.py
communex/balance.py
communex/cli/__init__.py
communex/cli/__main__.py
communex/cli/_common.py
communex/cli/balance.py
communex/cli/key.py
communex/cli/misc.py
communex/cli/module.py
communex/cli/network.py
communex/cli/root.py
communex/cli/subnet.py
communex/client.py
communex/compat/__init__.py
communex/compat/_util.py
communex/compat/key.py
communex/compat/storage.py
communex/compat/types.py
communex/encryption.py
communex/errors.py
communex/faucet/powv2.py
communex/key.py
communex/misc.py
communex/module/__init__.py
communex/module/_protocol.py
communex/module/_rate_limiters/_stake_limiter.py
communex/module/_rate_limiters/limiters.py
communex/module/_signer.py
communex/module/_util.py
communex/module/client.py
communex/module/example/__init__.py
communex/module/example/gpt.py
communex/module/example/openai.py
communex/module/module.py
communex/module/routers/module_routers.py
communex/module/server.py
communex/module/std/__init__.py
communex/module/std/whitelist_validator.py
communex/module/stuff.md
communex/password.py
communex/py.typed
communex/types.py
communex/util/__init__.py
communex/util/memo.py
communex/util/mutex.py
communex-0.1.36.5.dist-info/LICENSE
communex-0.1.36.5.dist-info/METADATA
communex-0.1.36.5.dist-info/WHEEL
communex-0.1.36.5.dist-info/entry_points.txt
communex-0.1.36.5.dist-info/RECORD
