Metadata-Version: 2.1
Name: communex
Version: 0.1.36.5
Summary: A library for Commune network focused on simplicity
License: MIT
Author: agicommies
Author-email: info@agicommies.org
Requires-Python: >=3.10,<4.0
Classifier: License :: OSI Approved :: MIT License
Classifier: Programming Language :: Python :: 3
Classifier: Programming Language :: Python :: 3.10
Classifier: Programming Language :: Python :: 3.11
Classifier: Programming Language :: Python :: 3.12
Classifier: Programming Language :: Python :: 3.13
Requires-Dist: aiohttp (>=3.9.3,<4.0.0)
Requires-Dist: cryptography (>=43.0.3,<44.0.0)
Requires-Dist: fastapi (>=0.110.0,<0.111.0)
Requires-Dist: keylimiter (>=0.1.5,<0.2.0)
Requires-Dist: py-sr25519-bindings (>=0.2.0,<0.3.0)
Requires-Dist: pydantic (>=2.6.4,<3.0.0)
Requires-Dist: pydantic-settings (>=2.2.1,<3.0.0)
Requires-Dist: rich (>=13.7.0,<14.0.0)
Requires-Dist: scalecodec (>=1.2.7,<2.0.0)
Requires-Dist: starlette (>=0.36.3,<0.37.0)
Requires-Dist: substrate-interface (>=1.7.4,<2.0.0)
Requires-Dist: typeguard (>=4.2.1,<5.0.0)
Requires-Dist: typer (>=0.9.0,<0.10.0)
Requires-Dist: uvicorn (>=0.29.0,<0.30.0)
